openbmi/bmi_gui.py
openbmi-0.1.dist-info/LICENSE
openbmi-0.1.dist-info/METADATA
openbmi-0.1.dist-info/WHEEL
openbmi-0.1.dist-info/top_level.txt
openbmi-0.1.dist-info/RECORD
