Metadata-Version: 2.1
Name: openbmi
Version: 0.1
Summary: open source [ca] bmi imaging tools
Home-page: https://github.com/catubc/bmi
Author: https://github.com/catubc/bmi
Author-email: <mitelutco@gmail.com>
Classifier: Programming Language :: Python :: 3
Classifier: License :: OSI Approved :: MIT License
Classifier: Operating System :: OS Independent
License-File: LICENSE
Requires-Dist: numpy
Requires-Dist: matplotlib
Requires-Dist: parmap
Requires-Dist: tqdm
Requires-Dist: scipy
Requires-Dist: opencv-python
Requires-Dist: scikit-learn
Requires-Dist: pandas
